{
  "team": [
    {
      "firstname": "Todd",
      "lastname": "Crandell",
      "github": "WoolenDoolen",
      "email": "tcrandel@ucsc.edu"
    },
    {
      "firstname": "Saurav",
      "lastname": "Shah",
      "github": "LegionDotEXE",
      "email": "sakushah@ucsc.edu"
    },
    {
      "firstname": "Branson",
      "lastname": "Guan",
      "github": "Dermisbakin",
      "email": "broguan@gmail.com"
    }
  ],
  "repository": "https://github.com/Dermisbakin/CMPM121Framework",
  "commit": "f1d57aacbf1d14de4c08a6b44f669ed0230860a6"
}
